{"fonts/Karla-Bold.ttf":["fonts/Karla-Bold.ttf"],"fonts/Karla-BoldItalic.ttf":["fonts/Karla-BoldItalic.ttf"],"fonts/Karla-Italic.ttf":["fonts/Karla-Italic.ttf"],"fonts/Karla-Regular.ttf":["fonts/Karla-Regular.ttf"],"fonts/LEMONMILK-Bold.otf":["fonts/LEMONMILK-Bold.otf"],"fonts/LEMONMILK-BoldItalic.otf":["fonts/LEMONMILK-BoldItalic.otf"],"fonts/LEMONMILK-Regular.otf":["fonts/LEMONMILK-Regular.otf"],"fonts/LEMONMILK-RegularItalic.otf":["fonts/LEMONMILK-RegularItalic.otf"],"fonts/Ubuntu-Bold.ttf":["fonts/Ubuntu-Bold.ttf"],"fonts/Ubuntu-BoldItalic.ttf":["fonts/Ubuntu-BoldItalic.ttf"],"fonts/Ubuntu-Italic.ttf":["fonts/Ubuntu-Italic.ttf"],"fonts/Ubuntu-Regular.ttf":["fonts/Ubuntu-Regular.ttf"],"images/league_logo.png":["images/league_logo.png"],"images/logos/abbrev/.DS_Store":["images/logos/abbrev/.DS_Store"],"images/logos/abbrev/abbrev-color.png":["images/logos/abbrev/abbrev-color.png"],"images/logos/abbrev/abbrev-mono-inv.png":["images/logos/abbrev/abbrev-mono-inv.png"],"images/logos/abbrev/abbrev-mono.png":["images/logos/abbrev/abbrev-mono.png"],"images/logos/abbrev/abbrev-tt.png":["images/logos/abbrev/abbrev-tt.png"],"images/logos/compact/.DS_Store":["images/logos/compact/.DS_Store"],"images/logos/compact/compact-color.png":["images/logos/compact/compact-color.png"],"images/logos/compact/compact-mono-inv.png":["images/logos/compact/compact-mono-inv.png"],"images/logos/compact/compact-mono.png":["images/logos/compact/compact-mono.png"],"images/logos/compact/compact-tt.png":["images/logos/compact/compact-tt.png"],"images/logos/full/.DS_Store":["images/logos/full/.DS_Store"],"images/logos/full/full-color.png":["images/logos/full/full-color.png"],"images/logos/full/full-mono-inv.png":["images/logos/full/full-mono-inv.png"],"images/logos/full/full-mono.png":["images/logos/full/full-mono.png"],"images/logos/full/full-tt.png":["images/logos/full/full-tt.png"],"images/logos/icon/.DS_Store":["images/logos/icon/.DS_Store"],"images/logos/icon/mark-color.png":["images/logos/icon/mark-color.png"],"images/logos/icon/mark-mono.png":["images/logos/icon/mark-mono.png"],"images/logos/icon/mark-tt.png":["images/logos/icon/mark-tt.png"],"images/ow_logo.png":["images/ow_logo.png"],"images/rocket_league_logo.png":["images/rocket_league_logo.png"],"images/splitgate_logo.png":["images/splitgate_logo.png"],"images/steam_logo.png":["images/steam_logo.png"],"images/valorant_logo.png":["images/valorant_logo.png"],"packages/cool_alert/assets/flare/error_check.flr":["packages/cool_alert/assets/flare/error_check.flr"],"packages/cool_alert/assets/flare/info_check.flr":["packages/cool_alert/assets/flare/info_check.flr"],"packages/cool_alert/assets/flare/loading.flr":["packages/cool_alert/assets/flare/loading.flr"],"packages/cool_alert/assets/flare/success_check.flr":["packages/cool_alert/assets/flare/success_check.flr"],"packages/cool_alert/assets/flare/warning_check.flr":["packages/cool_alert/assets/flare/warning_check.flr"],"packages/cupertino_icons/assets/CupertinoIcons.ttf":["packages/cupertino_icons/assets/CupertinoIcons.ttf"]}